{
  "data": [
    {
      "id": 1,
      "nome": "Ofélia",
      "sobrenome": "Barros",
      "email": "Isabela.Silva@yahoo.com",
      "fone": "(86) 0142-2717",
      "cargo": "Direct Configuration Facilitator"
    },
    {
      "id": 2,
      "nome": "Kléber",
      "sobrenome": "Moreira",
      "email": "Heitor.Batista90@bol.com.br",
      "fone": "+55 (99) 1659-6060",
      "cargo": "International Brand Assistant"
    },
    {
      "id": 3,
      "nome": "Karla",
      "sobrenome": "Melo",
      "email": "Alessandro.Santos@live.com",
      "fone": "(13) 6406-3984",
      "cargo": "Legacy Directives Coordinator"
    },
    {
      "id": 4,
      "nome": "Fabrício",
      "sobrenome": "Oliveira",
      "email": "Deneval.Pereira@bol.com.br",
      "fone": "+55 (87) 9806-8795",
      "cargo": "Direct Research Representative"
    },
    {
      "id": 5,
      "nome": "Sílvia",
      "sobrenome": "Souza",
      "email": "Jlia_Carvalho@bol.com.br",
      "fone": "(97) 8559-6795",
      "cargo": "Central Quality Liaison"
    },
    {
      "id": 6,
      "nome": "César",
      "sobrenome": "Moraes",
      "email": "Antnio37@bol.com.br",
      "fone": "(39) 0896-0804",
      "cargo": "Chief Usability Facilitator"
    },
    {
      "id": 7,
      "nome": "Roberta",
      "sobrenome": "Carvalho",
      "email": "Fabrcio.Martins@bol.com.br",
      "fone": "(40) 8003-5600",
      "cargo": "Chief Branding Planner"
    },
    {
      "id": 8,
      "nome": "Natália",
      "sobrenome": "Carvalho",
      "email": "Pablo.Batista95@hotmail.com",
      "fone": "(77) 2333-1600",
      "cargo": "District Factors Assistant"
    },
    {
      "id": 9,
      "nome": "Cecília",
      "sobrenome": "Braga",
      "email": "Yuri.Nogueira79@yahoo.com",
      "fone": "+55 (23) 1766-1056",
      "cargo": "International Communications Producer"
    },
    {
      "id": 10,
      "nome": "Frederico",
      "sobrenome": "Batista",
      "email": "Pedro28@gmail.com",
      "fone": "+55 (02) 4574-0067",
      "cargo": "International Solutions Consultant"
    },
    {
      "id": 11,
      "nome": "Vitória",
      "sobrenome": "Costa",
      "email": "Gbio.Albuquerque32@yahoo.com",
      "fone": "(27) 9883-7787",
      "cargo": "Corporate Implementation Supervisor"
    },
    {
      "id": 12,
      "nome": "Fabrícia",
      "sobrenome": "Barros",
      "email": "Janana.Carvalho74@bol.com.br",
      "fone": "(36) 6081-6818",
      "cargo": "Corporate Metrics Executive"
    },
    {
      "id": 13,
      "nome": "Janaína",
      "sobrenome": "Carvalho",
      "email": "Larissa.Barros26@gmail.com",
      "fone": "+55 (34) 5109-0695",
      "cargo": "Central Usability Agent"
    },
    {
      "id": 14,
      "nome": "Meire",
      "sobrenome": "Franco",
      "email": "Mrcia11@hotmail.com",
      "fone": "+55 (86) 6488-7603",
      "cargo": "Direct Web Consultant"
    },
    {
      "id": 15,
      "nome": "Gustavo",
      "sobrenome": "Nogueira",
      "email": "Fabrcia83@gmail.com",
      "fone": "(04) 28059-3968",
      "cargo": "Global Creative Liaison"
    },
    {
      "id": 16,
      "nome": "Alexandre",
      "sobrenome": "Souza",
      "email": "Fbio_Costa13@bol.com.br",
      "fone": "+55 (66) 5150-5011",
      "cargo": "Customer Creative Coordinator"
    },
    {
      "id": 17,
      "nome": "Elísio",
      "sobrenome": "Martins",
      "email": "Karla1@live.com",
      "fone": "(30) 5818-4563",
      "cargo": "Legacy Implementation Manager"
    },
    {
      "id": 18,
      "nome": "Sílvia",
      "sobrenome": "Carvalho",
      "email": "JlioCsar59@bol.com.br",
      "fone": "+55 (94) 8636-1664",
      "cargo": "District Creative Representative"
    },
    {
      "id": 19,
      "nome": "Mércia",
      "sobrenome": "Barros",
      "email": "Slvia_Saraiva16@hotmail.com",
      "fone": "+55 (72) 2092-7569",
      "cargo": "Customer Web Developer"
    },
    {
      "id": 20,
      "nome": "Antônio",
      "sobrenome": "Moraes",
      "email": "Janana_Reis59@bol.com.br",
      "fone": "+55 (55) 6208-4933",
      "cargo": "Dynamic Implementation Liaison"
    },
    {
      "id": 21,
      "nome": "Sílvia",
      "sobrenome": "Oliveira",
      "email": "Mrcia32@bol.com.br",
      "fone": "(82) 90537-4258",
      "cargo": "Legacy Interactions Planner"
    },
    {
      "id": 22,
      "nome": "Paula",
      "sobrenome": "Martins",
      "email": "Paulo_Silva10@gmail.com",
      "fone": "(27) 1668-8217",
      "cargo": "Product Functionality Assistant"
    },
    {
      "id": 23,
      "nome": "Ricardo",
      "sobrenome": "Albuquerque",
      "email": "Eduarda_Santos47@hotmail.com",
      "fone": "(53) 2669-9186",
      "cargo": "Global Identity Planner"
    },
    {
      "id": 24,
      "nome": "Júlia",
      "sobrenome": "Moraes",
      "email": "Feliciano.Braga@bol.com.br",
      "fone": "(83) 06769-6325",
      "cargo": "International Web Analyst"
    },
    {
      "id": 25,
      "nome": "Lorraine",
      "sobrenome": "Albuquerque",
      "email": "Lorraine_Saraiva13@live.com",
      "fone": "+55 (88) 6296-8257",
      "cargo": "Dynamic Intranet Designer"
    },
    {
      "id": 26,
      "nome": "Esther",
      "sobrenome": "Carvalho",
      "email": "Felcia_Martins@live.com",
      "fone": "(00) 0336-1695",
      "cargo": "Product Mobility Executive"
    },
    {
      "id": 27,
      "nome": "Marcos",
      "sobrenome": "Silva",
      "email": "Tertuliano_Albuquerque81@hotmail.com",
      "fone": "+55 (73) 8677-1559",
      "cargo": "Future Communications Consultant"
    },
    {
      "id": 28,
      "nome": "Félix",
      "sobrenome": "Braga",
      "email": "Fabrcia_Macedo33@hotmail.com",
      "fone": "(35) 48792-4147",
      "cargo": "Human Intranet Director"
    },
    {
      "id": 29,
      "nome": "Washington",
      "sobrenome": "Albuquerque",
      "email": "Sara.Carvalho@bol.com.br",
      "fone": "(67) 6331-6900",
      "cargo": "Future Mobility Consultant"
    },
    {
      "id": 30,
      "nome": "Carlos",
      "sobrenome": "Carvalho",
      "email": "Dalila.Nogueira@hotmail.com",
      "fone": "(27) 79129-2815",
      "cargo": "Corporate Tactics Assistant"
    },
    {
      "id": 31,
      "nome": "Lucas",
      "sobrenome": "Batista",
      "email": "Roberto.Oliveira@hotmail.com",
      "fone": "+55 (79) 4925-5232",
      "cargo": "Chief Creative Coordinator"
    },
    {
      "id": 32,
      "nome": "Pablo",
      "sobrenome": "Xavier",
      "email": "Lorena_Santos14@gmail.com",
      "fone": "(52) 99954-6770",
      "cargo": "Dynamic Usability Liaison"
    },
    {
      "id": 33,
      "nome": "Márcia",
      "sobrenome": "Xavier",
      "email": "Isabela.Santos@hotmail.com",
      "fone": "(43) 22329-6751",
      "cargo": "Lead Program Liaison"
    },
    {
      "id": 34,
      "nome": "Pablo",
      "sobrenome": "Melo",
      "email": "Carlos_Carvalho34@gmail.com",
      "fone": "+55 (63) 4868-6137",
      "cargo": "Human Assurance Engineer"
    },
    {
      "id": 35,
      "nome": "Rafael",
      "sobrenome": "Martins",
      "email": "Flix.Franco@gmail.com",
      "fone": "(61) 6808-1230",
      "cargo": "National Solutions Planner"
    },
    {
      "id": 36,
      "nome": "Felícia",
      "sobrenome": "Costa",
      "email": "Carlos0@live.com",
      "fone": "+55 (54) 6162-5803",
      "cargo": "Corporate Implementation Administrator"
    },
    {
      "id": 37,
      "nome": "Alessandro",
      "sobrenome": "Santos",
      "email": "Ladislau.Carvalho@yahoo.com",
      "fone": "(34) 70148-7648",
      "cargo": "Investor Division Orchestrator"
    },
    {
      "id": 38,
      "nome": "Eduardo",
      "sobrenome": "Xavier",
      "email": "Paula_Barros@yahoo.com",
      "fone": "(66) 48200-3129",
      "cargo": "Product Communications Manager"
    },
    {
      "id": 39,
      "nome": "Kléber",
      "sobrenome": "Moraes",
      "email": "Frederico18@yahoo.com",
      "fone": "(87) 9596-2987",
      "cargo": "Forward Branding Developer"
    },
    {
      "id": 40,
      "nome": "Kléber",
      "sobrenome": "Oliveira",
      "email": "Heitor_Batista@hotmail.com",
      "fone": "(97) 49541-2851",
      "cargo": "Dynamic Creative Engineer"
    },
    {
      "id": 41,
      "nome": "Lorena",
      "sobrenome": "Silva",
      "email": "Morgana85@live.com",
      "fone": "(26) 20600-3582",
      "cargo": "Forward Configuration Developer"
    },
    {
      "id": 42,
      "nome": "Morgana",
      "sobrenome": "Silva",
      "email": "Washington.Barros@yahoo.com",
      "fone": "+55 (87) 5943-4760",
      "cargo": "Global Tactics Engineer"
    },
    {
      "id": 43,
      "nome": "Márcia",
      "sobrenome": "Barros",
      "email": "Paulo95@bol.com.br",
      "fone": "+55 (49) 1587-7301",
      "cargo": "Future Program Architect"
    },
    {
      "id": 44,
      "nome": "Warley",
      "sobrenome": "Souza",
      "email": "Jlio52@bol.com.br",
      "fone": "(26) 8012-9902",
      "cargo": "Corporate Web Technician"
    },
    {
      "id": 45,
      "nome": "Yango",
      "sobrenome": "Pereira",
      "email": "Margarida_Melo77@yahoo.com",
      "fone": "(35) 28145-6587",
      "cargo": "Principal Integration Director"
    },
    {
      "id": 46,
      "nome": "Roberto",
      "sobrenome": "Oliveira",
      "email": "Elsio49@yahoo.com",
      "fone": "(63) 5471-8288",
      "cargo": "Future Accounts Administrator"
    },
    {
      "id": 47,
      "nome": "Lorraine",
      "sobrenome": "Nogueira",
      "email": "Silas.Melo@yahoo.com",
      "fone": "(59) 18985-4260",
      "cargo": "Chief Solutions Designer"
    },
    {
      "id": 48,
      "nome": "Fabiano",
      "sobrenome": "Moraes",
      "email": "Slvia.Martins@yahoo.com",
      "fone": "(75) 86838-5314",
      "cargo": "Regional Accountability Designer"
    },
    {
      "id": 49,
      "nome": "Sílvia",
      "sobrenome": "Silva",
      "email": "Pablo12@yahoo.com",
      "fone": "(26) 8253-7880",
      "cargo": "Internal Optimization Strategist"
    },
    {
      "id": 50,
      "nome": "Ofélia",
      "sobrenome": "Pereira",
      "email": "Feliciano.Nogueira85@live.com",
      "fone": "+55 (78) 0826-3492",
      "cargo": "Chief Usability Technician"
    },
    {
      "id": 51,
      "nome": "Isabel",
      "sobrenome": "Saraiva",
      "email": "Silas_Xavier@gmail.com",
      "fone": "+55 (55) 4125-2607",
      "cargo": "Legacy Usability Producer"
    },
    {
      "id": 52,
      "nome": "Karla",
      "sobrenome": "Braga",
      "email": "Gustavo_Nogueira18@gmail.com",
      "fone": "(98) 7529-9311",
      "cargo": "Senior Metrics Strategist"
    },
    {
      "id": 53,
      "nome": "Ladislau",
      "sobrenome": "Pereira",
      "email": "Rafaela_Pereira@bol.com.br",
      "fone": "(76) 8386-5197",
      "cargo": "Dynamic Implementation Consultant"
    },
    {
      "id": 54,
      "nome": "Júlio César",
      "sobrenome": "Barros",
      "email": "Salvador.Costa25@bol.com.br",
      "fone": "(95) 74245-3903",
      "cargo": "Legacy Group Developer"
    },
    {
      "id": 55,
      "nome": "Ígor",
      "sobrenome": "Nogueira",
      "email": "Marcelo94@gmail.com",
      "fone": "+55 (57) 1189-1765",
      "cargo": "Chief Usability Liaison"
    },
    {
      "id": 56,
      "nome": "Lucas",
      "sobrenome": "Pereira",
      "email": "Roberto_Moraes@gmail.com",
      "fone": "(41) 05186-7929",
      "cargo": "Legacy Integration Director"
    },
    {
      "id": 57,
      "nome": "Gúbio",
      "sobrenome": "Costa",
      "email": "Rafaela_Albuquerque@bol.com.br",
      "fone": "(00) 5129-3683",
      "cargo": "Future Integration Engineer"
    },
    {
      "id": 58,
      "nome": "Hugo",
      "sobrenome": "Saraiva",
      "email": "Lorraine82@live.com",
      "fone": "(97) 8628-1522",
      "cargo": "Future Quality Assistant"
    },
    {
      "id": 59,
      "nome": "Bruna",
      "sobrenome": "Franco",
      "email": "Eduarda.Braga54@hotmail.com",
      "fone": "(89) 21028-0407",
      "cargo": "District Infrastructure Specialist"
    },
    {
      "id": 60,
      "nome": "Feliciano",
      "sobrenome": "Santos",
      "email": "Bruna.Reis32@yahoo.com",
      "fone": "(67) 2112-4363",
      "cargo": "Regional Security Supervisor"
    },
    {
      "id": 61,
      "nome": "João",
      "sobrenome": "Braga",
      "email": "Sara.Xavier47@gmail.com",
      "fone": "(97) 84423-2600",
      "cargo": "Regional Interactions Liaison"
    },
    {
      "id": 62,
      "nome": "Gustavo",
      "sobrenome": "Souza",
      "email": "Norberto98@gmail.com",
      "fone": "(73) 90813-1206",
      "cargo": "Dynamic Branding Liaison"
    },
    {
      "id": 63,
      "nome": "Aline",
      "sobrenome": "Batista",
      "email": "Salvador11@bol.com.br",
      "fone": "(25) 3841-6708",
      "cargo": "Dynamic Metrics Agent"
    },
    {
      "id": 64,
      "nome": "Antônio",
      "sobrenome": "Santos",
      "email": "Silas_Xavier48@hotmail.com",
      "fone": "+55 (40) 6631-6169",
      "cargo": "Lead Group Assistant"
    },
    {
      "id": 65,
      "nome": "Talita",
      "sobrenome": "Barros",
      "email": "Frederico.Reis81@hotmail.com",
      "fone": "(89) 5062-4971",
      "cargo": "Human Marketing Orchestrator"
    },
    {
      "id": 66,
      "nome": "Eduardo",
      "sobrenome": "Reis",
      "email": "Jlio_Santos@bol.com.br",
      "fone": "(98) 77034-6852",
      "cargo": "Senior Usability Planner"
    },
    {
      "id": 67,
      "nome": "Isabela",
      "sobrenome": "Carvalho",
      "email": "Frederico.Macedo@hotmail.com",
      "fone": "(11) 76278-6568",
      "cargo": "Regional Configuration Officer"
    },
    {
      "id": 68,
      "nome": "Sirineu",
      "sobrenome": "Costa",
      "email": "Karla_Moraes6@gmail.com",
      "fone": "(77) 06991-1239",
      "cargo": "Dynamic Solutions Representative"
    },
    {
      "id": 69,
      "nome": "Larissa",
      "sobrenome": "Saraiva",
      "email": "Eduardo87@hotmail.com",
      "fone": "(98) 9261-0676",
      "cargo": "Regional Communications Manager"
    },
    {
      "id": 70,
      "nome": "Joana",
      "sobrenome": "Franco",
      "email": "Gbio_Silva9@yahoo.com",
      "fone": "+55 (64) 7921-1585",
      "cargo": "Dynamic Optimization Orchestrator"
    },
    {
      "id": 71,
      "nome": "Janaína",
      "sobrenome": "Melo",
      "email": "Margarida_Pereira4@bol.com.br",
      "fone": "+55 (67) 9760-0082",
      "cargo": "Lead Web Strategist"
    },
    {
      "id": 72,
      "nome": "Dalila",
      "sobrenome": "Reis",
      "email": "Aline_Saraiva@yahoo.com",
      "fone": "(32) 7036-2375",
      "cargo": "International Paradigm Assistant"
    },
    {
      "id": 73,
      "nome": "Felícia",
      "sobrenome": "Carvalho",
      "email": "Janana_Silva@bol.com.br",
      "fone": "+55 (42) 5883-0993",
      "cargo": "Product Factors Agent"
    },
    {
      "id": 74,
      "nome": "Marcela",
      "sobrenome": "Reis",
      "email": "Alexandre57@hotmail.com",
      "fone": "(09) 84491-0029",
      "cargo": "Lead Web Strategist"
    },
    {
      "id": 75,
      "nome": "Márcia",
      "sobrenome": "Xavier",
      "email": "Janana_Saraiva@bol.com.br",
      "fone": "(70) 6062-4177",
      "cargo": "Internal Brand Assistant"
    },
    {
      "id": 76,
      "nome": "Gustavo",
      "sobrenome": "Macedo",
      "email": "Vitria_Melo57@bol.com.br",
      "fone": "(90) 28969-8844",
      "cargo": "Investor Response Supervisor"
    },
    {
      "id": 77,
      "nome": "Márcia",
      "sobrenome": "Carvalho",
      "email": "Eduarda_Carvalho17@live.com",
      "fone": "(91) 3308-8851",
      "cargo": "Investor Accountability Assistant"
    },
    {
      "id": 78,
      "nome": "Maria",
      "sobrenome": "Carvalho",
      "email": "Slvia47@gmail.com",
      "fone": "(48) 34120-0833",
      "cargo": "International Implementation Facilitator"
    },
    {
      "id": 79,
      "nome": "Hugo",
      "sobrenome": "Pereira",
      "email": "Pablo9@gmail.com",
      "fone": "+55 (04) 7624-8625",
      "cargo": "Human Directives Executive"
    },
    {
      "id": 80,
      "nome": "Yango",
      "sobrenome": "Saraiva",
      "email": "Alexandre.Saraiva91@yahoo.com",
      "fone": "(22) 4122-6795",
      "cargo": "Dynamic Web Engineer"
    },
    {
      "id": 81,
      "nome": "Hélio",
      "sobrenome": "Macedo",
      "email": "Alessandra.Oliveira34@bol.com.br",
      "fone": "(53) 15298-0193",
      "cargo": "Global Markets Administrator"
    },
    {
      "id": 82,
      "nome": "Pablo",
      "sobrenome": "Braga",
      "email": "Jlio.Silva@bol.com.br",
      "fone": "(11) 78552-3579",
      "cargo": "Central Metrics Designer"
    },
    {
      "id": 83,
      "nome": "Bruna",
      "sobrenome": "Macedo",
      "email": "Alessandra28@live.com",
      "fone": "(08) 9030-7129",
      "cargo": "Legacy Functionality Designer"
    },
    {
      "id": 84,
      "nome": "Núbia",
      "sobrenome": "Souza",
      "email": "Alexandre57@hotmail.com",
      "fone": "(15) 88471-0092",
      "cargo": "Forward Security Producer"
    },
    {
      "id": 85,
      "nome": "Felícia",
      "sobrenome": "Braga",
      "email": "Guilherme.Batista@live.com",
      "fone": "(90) 8844-1549",
      "cargo": "National Intranet Representative"
    },
    {
      "id": 86,
      "nome": "Roberta",
      "sobrenome": "Saraiva",
      "email": "Pedro98@yahoo.com",
      "fone": "(54) 74337-8820",
      "cargo": "Customer Quality Officer"
    },
    {
      "id": 87,
      "nome": "Guilherme",
      "sobrenome": "Reis",
      "email": "Tertuliano.Albuquerque96@gmail.com",
      "fone": "(75) 10778-7520",
      "cargo": "International Paradigm Coordinator"
    },
    {
      "id": 88,
      "nome": "Júlio César",
      "sobrenome": "Pereira",
      "email": "Hugo_Costa81@yahoo.com",
      "fone": "(35) 7888-7277",
      "cargo": "Senior Research Representative"
    },
    {
      "id": 89,
      "nome": "Kléber",
      "sobrenome": "Martins",
      "email": "Eduardo63@hotmail.com",
      "fone": "(15) 63725-9084",
      "cargo": "Future Quality Engineer"
    },
    {
      "id": 90,
      "nome": "Eduardo",
      "sobrenome": "Oliveira",
      "email": "Vctor80@yahoo.com",
      "fone": "+55 (26) 0470-6012",
      "cargo": "Forward Accountability Administrator"
    },
    {
      "id": 91,
      "nome": "Marcelo",
      "sobrenome": "Reis",
      "email": "Vitria30@bol.com.br",
      "fone": "(59) 3180-9217",
      "cargo": "Product Functionality Manager"
    },
    {
      "id": 92,
      "nome": "Carlos",
      "sobrenome": "Silva",
      "email": "Paulo.Barros55@live.com",
      "fone": "(02) 1733-6052",
      "cargo": "National Division Facilitator"
    },
    {
      "id": 93,
      "nome": "Karla",
      "sobrenome": "Saraiva",
      "email": "Pablo74@yahoo.com",
      "fone": "(44) 59419-7057",
      "cargo": "Chief Markets Coordinator"
    },
    {
      "id": 94,
      "nome": "Margarida",
      "sobrenome": "Pereira",
      "email": "Sulen.Franco@yahoo.com",
      "fone": "+55 (66) 1585-1243",
      "cargo": "National Applications Executive"
    },
    {
      "id": 95,
      "nome": "Fabrícia",
      "sobrenome": "Pereira",
      "email": "Eduarda_Reis38@bol.com.br",
      "fone": "(54) 09700-6909",
      "cargo": "Direct Paradigm Planner"
    },
    {
      "id": 96,
      "nome": "Lorena",
      "sobrenome": "Braga",
      "email": "Meire.Barros@bol.com.br",
      "fone": "(16) 1515-5638",
      "cargo": "Legacy Branding Technician"
    },
    {
      "id": 97,
      "nome": "Margarida",
      "sobrenome": "Martins",
      "email": "Mrcia.Moraes24@yahoo.com",
      "fone": "+55 (34) 2393-7295",
      "cargo": "Dynamic Solutions Strategist"
    },
    {
      "id": 98,
      "nome": "Gustavo",
      "sobrenome": "Oliveira",
      "email": "Mrcia_Batista63@gmail.com",
      "fone": "(06) 08331-2110",
      "cargo": "Lead Markets Architect"
    },
    {
      "id": 99,
      "nome": "Sara",
      "sobrenome": "Moraes",
      "email": "Isabel37@live.com",
      "fone": "(66) 41263-1048",
      "cargo": "National Metrics Developer"
    },
    {
      "id": 100,
      "nome": "Elísio",
      "sobrenome": "Barros",
      "email": "Aline.Nogueira36@gmail.com",
      "fone": "+55 (91) 5688-8625",
      "cargo": "Senior Factors Consultant"
    }
  ],
  "estoque": [
    {
      "id": 1,
      "marca": "Audi",
      "uuid": "c460de61-e796-45c1-a38a-5c5435fbae17",
      "quant": 4,
      "disp": false
    },
    {
      "id": 2,
      "marca": "BMW",
      "uuid": "4d989e46-aecc-4bfb-a387-984abb59f08b",
      "quant": 10,
      "disp": true
    },
    {
      "id": 3,
      "marca": "Mercedes",
      "uuid": "4fea09b8-094e-4f2c-8a16-37f2f526cd31",
      "quant": 8,
      "disp": true
    },
    {
      "id": 4,
      "marca": "Porsche",
      "uuid": "52d79dbc-be80-4f46-a266-7b7cd520c994",
      "quant": 10,
      "disp": false
    },
    {
      "id": 5,
      "marca": "Volkswagen",
      "uuid": "2f58a6f8-1eec-405f-9a94-f389339acefd",
      "quant": 3,
      "disp": true
    },
    {
      "id": 6
    }
  ]
}